django_peppered_passwords/__init__.py
django_peppered_passwords/hashers.py
django_peppered_passwords-0.0.4.dist-info/METADATA
django_peppered_passwords-0.0.4.dist-info/WHEEL
django_peppered_passwords-0.0.4.dist-info/licenses/LICENSE
django_peppered_passwords-0.0.4.dist-info/RECORD
