Metadata-Version: 2.1
Name: django_peppered_passwords
Version: 0.0.4
Summary: Django hashed passwords with pepper
Project-URL: Homepage, https://github.com/fatih-erikli/django-peppered-passwords
Project-URL: Bug Tracker, https://github.com/fatih-erikli/django-peppered-passwords/issues
Author-email: Fatih Erikli <fatih.erikli.work@gmail.com>
License-File: LICENSE
Classifier: Operating System :: OS Independent
Classifier: Programming Language :: Python :: 3
Requires-Python: >=3.7
